Metadata-Version: 2.1
Name: neon-stt-plugin-deepspeech-stream-local
Version: 2.0.0
Summary: A Deepspeech Streaming stt plugin for Neon
Home-page: https://github.com/NeonGeckoCom/neon-stt-plugin-deepspeech_stream_local
Author: Neongecko
Author-email: developers@neon.ai
License: BSD-3
Keywords: mycroft plugin stt
Platform: UNKNOWN
Classifier: Intended Audience :: Developers
Classifier: Topic :: Text Processing :: Linguistic
Classifier: Programming Language :: Python :: 3.6
Requires-Dist: deepspeech (==0.9.3)
Requires-Dist: numpy (~=1.19)
Requires-Dist: SpeechRecognition (~=3.8)
Requires-Dist: ovos-plugin-manager (~=0.0.1)
Requires-Dist: huggingface-hub (~=0.4)
Requires-Dist: ovos-utils (~=0.0.23)
Requires-Dist: requests (~=2.20)
